deffcode/__init__.py
deffcode/ffdecoder.py
deffcode/ffhelper.py
deffcode/sourcer.py
deffcode/utils.py
deffcode/version.py
deffcode-0.2.6.dist-info/LICENSE
deffcode-0.2.6.dist-info/METADATA
deffcode-0.2.6.dist-info/WHEEL
deffcode-0.2.6.dist-info/top_level.txt
deffcode-0.2.6.dist-info/RECORD
