Metadata-Version: 2.1
Name: deffcode
Version: 0.2.6
Summary: A cross-platform High-performance & Flexible Real-time Video Frames Decoder in Python.
Home-page: https://abhitronix.github.io/deffcode
Author: Abhishek Thakur
Author-email: abhi.una12@gmail.com
License: Apache License 2.0
Project-URL: Bug Reports, https://github.com/abhiTronix/deffcode/issues
Project-URL: Funding, https://ko-fi.com/W7W8WTYO
Project-URL: Source, https://github.com/abhiTronix/deffcode
Project-URL: Documentation, https://abhitronix.github.io/deffcode
Project-URL: Changelog, https://abhitronix.github.io/deffcode/latest/changelog/
Keywords: FFmpeg,Decoder,Realtime,Framework,Cross-platform,Video Processing,Computer Vision,Video Decoding
Classifier: Development Status :: 5 - Production/Stable
Classifier: Operating System :: POSIX
Classifier: Operating System :: MacOS :: MacOS X
Classifier: Operating System :: Microsoft :: Windows
Classifier: Topic :: Multimedia :: Video
Classifier: Topic :: Multimedia :: Video :: Conversion
Classifier: Topic :: Scientific/Engineering
Classifier: Intended Audience :: Developers
Classifier: Intended Audience :: Science/Research
Classifier: Intended Audience :: Education
Classifier: License :: OSI Approved :: Apache Software License
Classifier: Programming Language :: Python :: 3.8
Classifier: Programming Language :: Python :: 3.9
Classifier: Programming Language :: Python :: 3.10
Classifier: Programming Language :: Python :: 3.11
Requires-Python: >=3.8
License-File: LICENSE
Requires-Dist: cython
Requires-Dist: numpy
Requires-Dist: requests
Requires-Dist: colorlog
Requires-Dist: tqdm
